<?xml version="1.0" encoding="utf-8" standalone="yes"?>
<DateArea>
	<date ID="10001" Name="小鸡" Icon="10001" ModelID="10001" Lv="1" UpTime="14400;43200;129600;172800" PeopleNum="1" ShowImgPro="0.6" BuyGold="800" SellGold="2000" DropTime="7200" GetPro="0.5" GetItemID="44000001" ShowItemID="11000001" GetItemIDNum="1" Speak="咕咕咕……" Des="咕咕咕……" Des_EN="" />
	<date ID="10002" Name="鸭子" Icon="10002" ModelID="10002" Lv="1" UpTime="14400;43200;129600;172800" PeopleNum="1" ShowImgPro="0.6" BuyGold="800" SellGold="2000" DropTime="7200" GetPro="0.5" GetItemID="44000002" ShowItemID="11000002" GetItemIDNum="1" Speak="嘎嘎嘎……" Des="嘎嘎嘎……" Des_EN="" />
	<date ID="10003" Name="公鸡" Icon="10003" ModelID="10003" Lv="2" UpTime="14400;43200;129600;172800" PeopleNum="1" ShowImgPro="0.5" BuyGold="1000" SellGold="2200" DropTime="7200" GetPro="0.5" GetItemID="44000003" ShowItemID="11000003" GetItemIDNum="1" Speak="咯咯哒……咯咯哒……" Des="咯咯哒……咯咯哒……" Des_EN="" />
	<date ID="10004" Name="兔子" Icon="10004" ModelID="10004" Lv="4" UpTime="14400;43200;129600;172800" PeopleNum="2" ShowImgPro="0.5" BuyGold="2600" SellGold="5200" DropTime="7200" GetPro="0.5" GetItemID="44000004" ShowItemID="11000004" GetItemIDNum="1" Speak="你看见我的耳朵了嘛？" Des="你看见我的耳朵了嘛？" Des_EN="" />
	<date ID="10005" Name="猫" Icon="10005" ModelID="10005" Lv="6" UpTime="14400;43200;129600;172800" PeopleNum="2" ShowImgPro="0.5" BuyGold="3100" SellGold="5600" DropTime="7200" GetPro="0.5" GetItemID="44000005" ShowItemID="11000005" GetItemIDNum="1" Speak="在哪里有吃的呢" Des="在哪里有吃的呢" Des_EN="" />
	<date ID="10006" Name="猪" Icon="10006" ModelID="10006" Lv="8" UpTime="14400;43200;129600;172800" PeopleNum="2" ShowImgPro="0.4" BuyGold="3600" SellGold="6000" DropTime="7200" GetPro="0.5" GetItemID="44000006" ShowItemID="11000006" GetItemIDNum="1" Speak="别打扰我,我要睡一会儿" Des="别打扰我,我要睡一会儿" Des_EN="" />
	<date ID="10007" Name="公牛" Icon="10007" ModelID="10007" Lv="10" UpTime="14400;43200;129600;172800" PeopleNum="3" ShowImgPro="0.3" BuyGold="6800" SellGold="10400" DropTime="7200" GetPro="0.5" GetItemID="44000007" ShowItemID="11000007" GetItemIDNum="1" Speak="哞哞……" Des="哞哞……" Des_EN="" />
	<date ID="10008" Name="绵羊" Icon="10008" ModelID="10008" Lv="12" UpTime="14400;43200;129600;172800" PeopleNum="3" ShowImgPro="0.35" BuyGold="7800" SellGold="11200" DropTime="7200" GetPro="0.5" GetItemID="44000008" ShowItemID="11000008" GetItemIDNum="1" Speak="咩……" Des="咩……" Des_EN="" />
	<date ID="10009" Name="野猪" Icon="10009" ModelID="10009" Lv="14" UpTime="14400;43200;129600;172800" PeopleNum="4" ShowImgPro="0.35" BuyGold="12600" SellGold="16800" DropTime="7200" GetPro="0.5" GetItemID="44000009" ShowItemID="11000009" GetItemIDNum="1" Speak="我的牙齿可是很坚的喔~" Des="我的牙齿可是很坚的喔~" Des_EN="" />
	<date ID="10010" Name="奶牛" Icon="10010" ModelID="10010" Lv="16" UpTime="14400;43200;129600;172800" PeopleNum="4" ShowImgPro="0.3" BuyGold="14400" SellGold="18000" DropTime="7200" GetPro="0.5" GetItemID="44000010" ShowItemID="11000010" GetItemIDNum="1" Speak="别挤了,我真的没奶了!" Des="别挤了,我真的没奶了!" Des_EN="" />
	<date ID="10011" Name="山羊" Icon="10011" ModelID="10011" Lv="18" UpTime="14400;43200;129600;172800" PeopleNum="5" ShowImgPro="0.35" BuyGold="19800" SellGold="24800" DropTime="7200" GetPro="0.5" GetItemID="44000011" ShowItemID="11000011" GetItemIDNum="1" Speak="我想变成一只战斗山羊" Des="我想变成一只战斗山羊" Des_EN="" />
	<date ID="10012" Name="马" Icon="10012" ModelID="10012" Lv="20" UpTime="14400;43200;129600;172800" PeopleNum="5" ShowImgPro="0.35" BuyGold="20800" SellGold="26000" DropTime="7200" GetPro="0.5" GetItemID="44000012" ShowItemID="11000012" GetItemIDNum="1" Speak="我们来比赛赛跑吧?" Des="我们来比赛赛跑吧?" Des_EN="" />
</DateArea>