<?xml version="1.0" encoding="utf-8" standalone="yes"?>
<DateArea>
	<date ID="10001" EventType="3" EventItemID="10030207" EventLv="1" EventPro="1" EventItemNum="1" CurrencyType="1" CurrencyNum="13920" EventTime="300" EventDes="村民在村中意外发了这个道具,如果你可以出个好价格的话，它就是你的了！" />
	<date ID="10002" EventType="3" EventItemID="10030214" EventLv="1" EventPro="1" EventItemNum="1" CurrencyType="1" CurrencyNum="21000" EventTime="300" EventDes="村民在村中意外发了这个道具,如果你可以出个好价格的话，它就是你的了！" />
	<date ID="10003" EventType="3" EventItemID="10030217" EventLv="1" EventPro="1" EventItemNum="1" CurrencyType="1" CurrencyNum="46800" EventTime="300" EventDes="村民在村中意外发了这个道具,如果你可以出个好价格的话，它就是你的了！" />
	<date ID="10004" EventType="3" EventItemID="10030222" EventLv="1" EventPro="1" EventItemNum="1" CurrencyType="1" CurrencyNum="48420" EventTime="300" EventDes="村民在村中意外发了这个道具,如果你可以出个好价格的话，它就是你的了！" />
	<date ID="10005" EventType="3" EventItemID="10030260" EventLv="1" EventPro="1" EventItemNum="1" CurrencyType="1" CurrencyNum="22800" EventTime="300" EventDes="村民在村中意外发了这个道具,如果你可以出个好价格的话，它就是你的了！" />
	<date ID="10006" EventType="3" EventItemID="10030261" EventLv="1" EventPro="1" EventItemNum="1" CurrencyType="1" CurrencyNum="22800" EventTime="300" EventDes="村民在村中意外发了这个道具,如果你可以出个好价格的话，它就是你的了！" />
	<date ID="10007" EventType="3" EventItemID="10030262" EventLv="1" EventPro="1" EventItemNum="1" CurrencyType="1" CurrencyNum="22800" EventTime="300" EventDes="村民在村中意外发了这个道具,如果你可以出个好价格的话，它就是你的了！" />
	<date ID="10008" EventType="3" EventItemID="10010061" EventLv="1" EventPro="1" EventItemNum="10" CurrencyType="1" CurrencyNum="35880" EventTime="300" EventDes="村民在村中意外发了这个道具,如果你可以出个好价格的话，它就是你的了！" />
	<date ID="10009" EventType="3" EventItemID="10020010" EventLv="1" EventPro="1" EventItemNum="1" CurrencyType="1" CurrencyNum="3420" EventTime="300" EventDes="村民在村中意外发了这个道具,如果你可以出个好价格的话，它就是你的了！" />
	<date ID="10010" EventType="3" EventItemID="10030219" EventLv="1" EventPro="1" EventItemNum="1" CurrencyType="1" CurrencyNum="96840" EventTime="300" EventDes="村民在村中意外发了这个道具,如果你可以出个好价格的话，它就是你的了！" />
	<date ID="10011" EventType="3" EventItemID="10030220" EventLv="1" EventPro="1" EventItemNum="1" CurrencyType="1" CurrencyNum="117000" EventTime="300" EventDes="村民在村中意外发了这个道具,如果你可以出个好价格的话，它就是你的了！" />
	<date ID="10012" EventType="3" EventItemID="10020016" EventLv="1" EventPro="1" EventItemNum="20" CurrencyType="1" CurrencyNum="2340" EventTime="300" EventDes="村民在村中意外发了这个道具,如果你可以出个好价格的话，它就是你的了！" />
	<date ID="10013" EventType="3" EventItemID="10020017" EventLv="1" EventPro="1" EventItemNum="20" CurrencyType="1" CurrencyNum="4100" EventTime="300" EventDes="村民在村中意外发了这个道具,如果你可以出个好价格的话，它就是你的了！" />
	<date ID="10014" EventType="3" EventItemID="10020015" EventLv="1" EventPro="1" EventItemNum="1" CurrencyType="1" CurrencyNum="11700" EventTime="300" EventDes="村民在村中意外发了这个道具,如果你可以出个好价格的话，它就是你的了！" />
	<date ID="10015" EventType="2" EventItemID="10020002" EventLv="1" EventPro="1" EventItemNum="20" CurrencyType="1" CurrencyNum="1500" EventTime="300" EventDes="我现在正在收购这个材料,如果你有的话,我可以高价收购！" />
	<date ID="10016" EventType="2" EventItemID="10020003" EventLv="1" EventPro="1" EventItemNum="20" CurrencyType="1" CurrencyNum="1200" EventTime="300" EventDes="我现在正在收购这个材料,如果你有的话,我可以高价收购！" />
	<date ID="10017" EventType="2" EventItemID="10020005" EventLv="1" EventPro="1" EventItemNum="20" CurrencyType="1" CurrencyNum="2400" EventTime="300" EventDes="我现在正在收购这个材料,如果你有的话,我可以高价收购！" />
	<date ID="10018" EventType="2" EventItemID="10020007" EventLv="1" EventPro="1" EventItemNum="20" CurrencyType="1" CurrencyNum="1700" EventTime="300" EventDes="我现在正在收购这个材料,如果你有的话,我可以高价收购！" />
	<date ID="10019" EventType="2" EventItemID="10020008" EventLv="1" EventPro="1" EventItemNum="20" CurrencyType="1" CurrencyNum="3300" EventTime="300" EventDes="我现在正在收购这个材料,如果你有的话,我可以高价收购！" />
	<date ID="10020" EventType="2" EventItemID="10020009" EventLv="1" EventPro="1" EventItemNum="20" CurrencyType="1" CurrencyNum="3300" EventTime="300" EventDes="我现在正在收购这个材料,如果你有的话,我可以高价收购！" />
	<date ID="10021" EventType="2" EventItemID="10020010" EventLv="1" EventPro="1" EventItemNum="1" CurrencyType="1" CurrencyNum="22800" EventTime="300" EventDes="我现在正在收购这个材料,如果你有的话,我可以高价收购！" />
	<date ID="10022" EventType="2" EventItemID="10020011" EventLv="1" EventPro="1" EventItemNum="20" CurrencyType="1" CurrencyNum="4700" EventTime="300" EventDes="我现在正在收购这个材料,如果你有的话,我可以高价收购！" />
	<date ID="10023" EventType="2" EventItemID="10020012" EventLv="1" EventPro="1" EventItemNum="20" CurrencyType="1" CurrencyNum="5100" EventTime="300" EventDes="我现在正在收购这个材料,如果你有的话,我可以高价收购！" />
	<date ID="10024" EventType="2" EventItemID="10020013" EventLv="1" EventPro="1" EventItemNum="20" CurrencyType="1" CurrencyNum="5600" EventTime="300" EventDes="我现在正在收购这个材料,如果你有的话,我可以高价收购！" />
	<date ID="10025" EventType="2" EventItemID="10020014" EventLv="1" EventPro="1" EventItemNum="20" CurrencyType="1" CurrencyNum="6000" EventTime="300" EventDes="我现在正在收购这个材料,如果你有的话,我可以高价收购！" />
	<date ID="10026" EventType="1" EventItemID="10020002" EventLv="1" EventPro="1" EventItemNum="20" CurrencyType="1" CurrencyNum="750" EventTime="300" EventDes="村里多了一些材料,就便宜卖给你吧!" />
	<date ID="10027" EventType="1" EventItemID="10020003" EventLv="1" EventPro="1" EventItemNum="20" CurrencyType="1" CurrencyNum="600" EventTime="300" EventDes="村里多了一些材料,就便宜卖给你吧!" />
	<date ID="10028" EventType="1" EventItemID="10020005" EventLv="1" EventPro="1" EventItemNum="20" CurrencyType="1" CurrencyNum="1200" EventTime="300" EventDes="村里多了一些材料,就便宜卖给你吧!" />
	<date ID="10029" EventType="1" EventItemID="10020007" EventLv="1" EventPro="1" EventItemNum="20" CurrencyType="1" CurrencyNum="850" EventTime="300" EventDes="村里多了一些材料,就便宜卖给你吧!" />
	<date ID="10030" EventType="1" EventItemID="10020008" EventLv="1" EventPro="1" EventItemNum="20" CurrencyType="1" CurrencyNum="1650" EventTime="300" EventDes="村里多了一些材料,就便宜卖给你吧!" />
	<date ID="10031" EventType="1" EventItemID="10020009" EventLv="1" EventPro="1" EventItemNum="20" CurrencyType="1" CurrencyNum="1650" EventTime="300" EventDes="村里多了一些材料,就便宜卖给你吧!" />
	<date ID="10032" EventType="1" EventItemID="10020010" EventLv="1" EventPro="1" EventItemNum="20" CurrencyType="1" CurrencyNum="11400" EventTime="300" EventDes="村里多了一些材料,就便宜卖给你吧!" />
	<date ID="10033" EventType="1" EventItemID="10020011" EventLv="1" EventPro="1" EventItemNum="20" CurrencyType="1" CurrencyNum="2350" EventTime="300" EventDes="村里多了一些材料,就便宜卖给你吧!" />
	<date ID="10034" EventType="1" EventItemID="10020012" EventLv="1" EventPro="1" EventItemNum="20" CurrencyType="1" CurrencyNum="2550" EventTime="300" EventDes="村里多了一些材料,就便宜卖给你吧!" />
	<date ID="10035" EventType="1" EventItemID="10020013" EventLv="1" EventPro="1" EventItemNum="20" CurrencyType="1" CurrencyNum="2800" EventTime="300" EventDes="村里多了一些材料,就便宜卖给你吧!" />
	<date ID="10036" EventType="1" EventItemID="10020014" EventLv="1" EventPro="1" EventItemNum="20" CurrencyType="1" CurrencyNum="3000" EventTime="300" EventDes="村里多了一些材料,就便宜卖给你吧!" />
	<date ID="20001" EventType="3" EventItemID="10010209" EventLv="18" EventPro=".5" EventItemNum="1" CurrencyType="1" CurrencyNum="46125" EventTime="300" EventDes="村民在村中意外发了这个道具,如果你可以出个好价格的话，它就是你的了！" />
	<date ID="20002" EventType="3" EventItemID="10010210" EventLv="18" EventPro=".5" EventItemNum="1" CurrencyType="1" CurrencyNum="63750" EventTime="300" EventDes="村民在村中意外发了这个道具,如果你可以出个好价格的话，它就是你的了！" />
	<date ID="20003" EventType="3" EventItemID="10010211" EventLv="18" EventPro=".5" EventItemNum="1" CurrencyType="1" CurrencyNum="49500" EventTime="300" EventDes="村民在村中意外发了这个道具,如果你可以出个好价格的话，它就是你的了！" />
	<date ID="20004" EventType="3" EventItemID="10010212" EventLv="25" EventPro=".5" EventItemNum="1" CurrencyType="1" CurrencyNum="102375" EventTime="300" EventDes="村民在村中意外发了这个道具,如果你可以出个好价格的话，它就是你的了！" />
	<date ID="20005" EventType="3" EventItemID="10030301" EventLv="20" EventPro=".5" EventItemNum="1" CurrencyType="1" CurrencyNum="276600" EventTime="300" EventDes="村民在村中意外发了这个道具,如果你可以出个好价格的话，它就是你的了！" />
	<date ID="20006" EventType="3" EventItemID="10030303" EventLv="20" EventPro=".5" EventItemNum="1" CurrencyType="1" CurrencyNum="251400" EventTime="300" EventDes="村民在村中意外发了这个道具,如果你可以出个好价格的话，它就是你的了！" />
	<date ID="20007" EventType="3" EventItemID="10030305" EventLv="20" EventPro=".5" EventItemNum="1" CurrencyType="1" CurrencyNum="201000" EventTime="300" EventDes="村民在村中意外发了这个道具,如果你可以出个好价格的话，它就是你的了！" />
	<date ID="20008" EventType="3" EventItemID="10030307" EventLv="20" EventPro=".5" EventItemNum="1" CurrencyType="1" CurrencyNum="201000" EventTime="300" EventDes="村民在村中意外发了这个道具,如果你可以出个好价格的话，它就是你的了！" />
	<date ID="20009" EventType="3" EventItemID="10030309" EventLv="20" EventPro=".5" EventItemNum="1" CurrencyType="1" CurrencyNum="301800" EventTime="300" EventDes="村民在村中意外发了这个道具,如果你可以出个好价格的话，它就是你的了！" />
	<date ID="20010" EventType="3" EventItemID="10030311" EventLv="20" EventPro=".5" EventItemNum="1" CurrencyType="1" CurrencyNum="327000" EventTime="300" EventDes="村民在村中意外发了这个道具,如果你可以出个好价格的话，它就是你的了！" />
	<date ID="20011" EventType="3" EventItemID="10030313" EventLv="20" EventPro=".5" EventItemNum="1" CurrencyType="1" CurrencyNum="402000" EventTime="300" EventDes="村民在村中意外发了这个道具,如果你可以出个好价格的话，它就是你的了！" />
	<date ID="20012" EventType="3" EventItemID="10030315" EventLv="20" EventPro=".5" EventItemNum="1" CurrencyType="1" CurrencyNum="955200" EventTime="300" EventDes="村民在村中意外发了这个道具,如果你可以出个好价格的话，它就是你的了！" />
	<date ID="20013" EventType="3" EventItemID="10030316" EventLv="20" EventPro=".5" EventItemNum="1" CurrencyType="1" CurrencyNum="603600" EventTime="300" EventDes="村民在村中意外发了这个道具,如果你可以出个好价格的话，它就是你的了！" />
	<date ID="20014" EventType="3" EventItemID="10030317" EventLv="20" EventPro=".2" EventItemNum="1" CurrencyType="1" CurrencyNum="1508400" EventTime="300" EventDes="村民在村中意外发了这个道具,如果你可以出个好价格的话，它就是你的了！" />
	<date ID="20015" EventType="3" EventItemID="10030320" EventLv="20" EventPro=".2" EventItemNum="1" CurrencyType="1" CurrencyNum="754200" EventTime="300" EventDes="村民在村中意外发了这个道具,如果你可以出个好价格的话，它就是你的了！" />
	<date ID="20016" EventType="3" EventItemID="10030318" EventLv="18" EventPro=".5" EventItemNum="1" CurrencyType="1" CurrencyNum="90450" EventTime="300" EventDes="村民在村中意外发了这个道具,如果你可以出个好价格的话，它就是你的了！" />
	<date ID="20017" EventType="3" EventItemID="10030319" EventLv="18" EventPro=".5" EventItemNum="1" CurrencyType="1" CurrencyNum="150750" EventTime="300" EventDes="村民在村中意外发了这个道具,如果你可以出个好价格的话，它就是你的了！" />
	<date ID="20018" EventType="3" EventItemID="10010062" EventLv="18" EventPro=".5" EventItemNum="10" CurrencyType="1" CurrencyNum="67320" EventTime="300" EventDes="村民在村中意外发了这个道具,如果你可以出个好价格的话，它就是你的了！" />
	<date ID="20019" EventType="3" EventItemID="10020063" EventLv="25" EventPro=".5" EventItemNum="1" CurrencyType="1" CurrencyNum="61500" EventTime="300" EventDes="村民在村中意外发了这个道具,如果你可以出个好价格的话，它就是你的了！" />
	<date ID="20020" EventType="3" EventItemID="10010213" EventLv="25" EventPro=".1" EventItemNum="1" CurrencyType="1" CurrencyNum="1057500" EventTime="300" EventDes="村民在村中意外发了这个道具,如果你可以出个好价格的话，它就是你的了！" />
	<date ID="20021" EventType="3" EventItemID="10010214" EventLv="25" EventPro=".1" EventItemNum="1" CurrencyType="1" CurrencyNum="881250" EventTime="300" EventDes="村民在村中意外发了这个道具,如果你可以出个好价格的话，它就是你的了！" />
	<date ID="20022" EventType="3" EventItemID="10020056" EventLv="18" EventPro=".5" EventItemNum="1" CurrencyType="1" CurrencyNum="27675" EventTime="300" EventDes="村民在村中意外发了这个道具,如果你可以出个好价格的话，它就是你的了！" />
	<date ID="20023" EventType="3" EventItemID="10020058" EventLv="18" EventPro="1" EventItemNum="20" CurrencyType="1" CurrencyNum="3690" EventTime="300" EventDes="村民在村中意外发了这个道具,如果你可以出个好价格的话，它就是你的了！" />
	<date ID="20024" EventType="3" EventItemID="10020059" EventLv="18" EventPro="1" EventItemNum="20" CurrencyType="1" CurrencyNum="6460" EventTime="300" EventDes="村民在村中意外发了这个道具,如果你可以出个好价格的话，它就是你的了！" />
	<date ID="20025" EventType="2" EventItemID="10020052" EventLv="18" EventPro="1" EventItemNum="20" CurrencyType="1" CurrencyNum="9200" EventTime="300" EventDes="我现在正在收购这个材料,如果你有的话,我可以高价收购！" />
	<date ID="20026" EventType="2" EventItemID="10020053" EventLv="18" EventPro="1" EventItemNum="20" CurrencyType="1" CurrencyNum="9600" EventTime="300" EventDes="我现在正在收购这个材料,如果你有的话,我可以高价收购！" />
	<date ID="20027" EventType="2" EventItemID="10020054" EventLv="20" EventPro="1" EventItemNum="20" CurrencyType="1" CurrencyNum="10100" EventTime="300" EventDes="我现在正在收购这个材料,如果你有的话,我可以高价收购！" />
	<date ID="20028" EventType="2" EventItemID="10020055" EventLv="22" EventPro="1" EventItemNum="20" CurrencyType="1" CurrencyNum="10500" EventTime="300" EventDes="我现在正在收购这个材料,如果你有的话,我可以高价收购！" />
	<date ID="20029" EventType="2" EventItemID="10020057" EventLv="22" EventPro="1" EventItemNum="20" CurrencyType="1" CurrencyNum="11400" EventTime="300" EventDes="我现在正在收购这个材料,如果你有的话,我可以高价收购！" />
	<date ID="20030" EventType="2" EventItemID="10020060" EventLv="20" EventPro="1" EventItemNum="20" CurrencyType="1" CurrencyNum="7600" EventTime="300" EventDes="我现在正在收购这个材料,如果你有的话,我可以高价收购！" />
	<date ID="20031" EventType="2" EventItemID="10020061" EventLv="22" EventPro="1" EventItemNum="20" CurrencyType="1" CurrencyNum="12300" EventTime="300" EventDes="我现在正在收购这个材料,如果你有的话,我可以高价收购！" />
	<date ID="20032" EventType="1" EventItemID="10020052" EventLv="18" EventPro="1" EventItemNum="20" CurrencyType="1" CurrencyNum="4600" EventTime="300" EventDes="村里多了一些材料,就便宜卖给你吧!" />
	<date ID="20033" EventType="1" EventItemID="10020053" EventLv="18" EventPro="1" EventItemNum="20" CurrencyType="1" CurrencyNum="4800" EventTime="300" EventDes="村里多了一些材料,就便宜卖给你吧!" />
	<date ID="20034" EventType="1" EventItemID="10020054" EventLv="20" EventPro="1" EventItemNum="20" CurrencyType="1" CurrencyNum="5050" EventTime="300" EventDes="村里多了一些材料,就便宜卖给你吧!" />
	<date ID="20035" EventType="1" EventItemID="10020055" EventLv="22" EventPro="1" EventItemNum="20" CurrencyType="1" CurrencyNum="5250" EventTime="300" EventDes="村里多了一些材料,就便宜卖给你吧!" />
	<date ID="20036" EventType="1" EventItemID="10020057" EventLv="22" EventPro="1" EventItemNum="20" CurrencyType="1" CurrencyNum="5700" EventTime="300" EventDes="村里多了一些材料,就便宜卖给你吧!" />
	<date ID="20037" EventType="1" EventItemID="10020060" EventLv="20" EventPro="1" EventItemNum="20" CurrencyType="1" CurrencyNum="3800" EventTime="300" EventDes="村里多了一些材料,就便宜卖给你吧!" />
	<date ID="20038" EventType="1" EventItemID="10020061" EventLv="22" EventPro="1" EventItemNum="20" CurrencyType="1" CurrencyNum="6150" EventTime="300" EventDes="村里多了一些材料,就便宜卖给你吧!" />
	<date ID="30001" EventType="3" EventItemID="10010306" EventLv="30" EventPro=".5" EventItemNum="1" CurrencyType="1" CurrencyNum="63000" EventTime="300" EventDes="村民在村中意外发了这个道具,如果你可以出个好价格的话，它就是你的了！" />
	<date ID="30002" EventType="3" EventItemID="10010307" EventLv="30" EventPro=".5" EventItemNum="1" CurrencyType="1" CurrencyNum="86250" EventTime="300" EventDes="村民在村中意外发了这个道具,如果你可以出个好价格的话，它就是你的了！" />
	<date ID="30003" EventType="3" EventItemID="10010308" EventLv="30" EventPro=".5" EventItemNum="1" CurrencyType="1" CurrencyNum="66375" EventTime="300" EventDes="村民在村中意外发了这个道具,如果你可以出个好价格的话，它就是你的了！" />
	<date ID="30004" EventType="3" EventItemID="10010309" EventLv="35" EventPro=".5" EventItemNum="1" CurrencyType="1" CurrencyNum="186000" EventTime="300" EventDes="村民在村中意外发了这个道具,如果你可以出个好价格的话，它就是你的了！" />
	<date ID="30005" EventType="3" EventItemID="10030401" EventLv="30" EventPro=".5" EventItemNum="1" CurrencyType="1" CurrencyNum="400200" EventTime="300" EventDes="村民在村中意外发了这个道具,如果你可以出个好价格的话，它就是你的了！" />
	<date ID="30006" EventType="3" EventItemID="10030403" EventLv="30" EventPro=".5" EventItemNum="1" CurrencyType="1" CurrencyNum="364200" EventTime="300" EventDes="村民在村中意外发了这个道具,如果你可以出个好价格的话，它就是你的了！" />
	<date ID="30007" EventType="3" EventItemID="10030405" EventLv="30" EventPro=".5" EventItemNum="1" CurrencyType="1" CurrencyNum="291000" EventTime="300" EventDes="村民在村中意外发了这个道具,如果你可以出个好价格的话，它就是你的了！" />
	<date ID="30008" EventType="3" EventItemID="10030407" EventLv="30" EventPro=".5" EventItemNum="1" CurrencyType="1" CurrencyNum="291000" EventTime="300" EventDes="村民在村中意外发了这个道具,如果你可以出个好价格的话，它就是你的了！" />
	<date ID="30009" EventType="3" EventItemID="10030409" EventLv="30" EventPro=".5" EventItemNum="1" CurrencyType="1" CurrencyNum="436800" EventTime="300" EventDes="村民在村中意外发了这个道具,如果你可以出个好价格的话，它就是你的了！" />
	<date ID="30010" EventType="3" EventItemID="10030411" EventLv="30" EventPro=".5" EventItemNum="1" CurrencyType="1" CurrencyNum="472800" EventTime="300" EventDes="村民在村中意外发了这个道具,如果你可以出个好价格的话，它就是你的了！" />
	<date ID="30011" EventType="3" EventItemID="10030413" EventLv="30" EventPro=".5" EventItemNum="1" CurrencyType="1" CurrencyNum="582000" EventTime="300" EventDes="村民在村中意外发了这个道具,如果你可以出个好价格的话，它就是你的了！" />
	<date ID="30012" EventType="3" EventItemID="10030415" EventLv="30" EventPro=".5" EventItemNum="1" CurrencyType="1" CurrencyNum="1383000" EventTime="300" EventDes="村民在村中意外发了这个道具,如果你可以出个好价格的话，它就是你的了！" />
	<date ID="30013" EventType="3" EventItemID="10030416" EventLv="30" EventPro=".5" EventItemNum="1" CurrencyType="1" CurrencyNum="873600" EventTime="300" EventDes="村民在村中意外发了这个道具,如果你可以出个好价格的话，它就是你的了！" />
	<date ID="30014" EventType="3" EventItemID="10030418" EventLv="30" EventPro=".2" EventItemNum="1" CurrencyType="1" CurrencyNum="2183400" EventTime="300" EventDes="村民在村中意外发了这个道具,如果你可以出个好价格的话，它就是你的了！" />
	<date ID="30015" EventType="3" EventItemID="10030420" EventLv="30" EventPro=".2" EventItemNum="1" CurrencyType="1" CurrencyNum="1092000" EventTime="300" EventDes="村民在村中意外发了这个道具,如果你可以出个好价格的话，它就是你的了！" />
	<date ID="30016" EventType="3" EventItemID="10030419" EventLv="30" EventPro=".5" EventItemNum="1" CurrencyType="1" CurrencyNum="327510" EventTime="300" EventDes="村民在村中意外发了这个道具,如果你可以出个好价格的话，它就是你的了！" />
	<date ID="30017" EventType="3" EventItemID="10010063" EventLv="30" EventPro=".5" EventItemNum="1" CurrencyType="1" CurrencyNum="140280" EventTime="300" EventDes="村民在村中意外发了这个道具,如果你可以出个好价格的话，它就是你的了！" />
	<date ID="30018" EventType="3" EventItemID="10020108" EventLv="30" EventPro=".5" EventItemNum="20" CurrencyType="1" CurrencyNum="5040" EventTime="300" EventDes="村民在村中意外发了这个道具,如果你可以出个好价格的话，它就是你的了！" />
	<date ID="30019" EventType="3" EventItemID="10020109" EventLv="30" EventPro=".5" EventItemNum="20" CurrencyType="1" CurrencyNum="8820" EventTime="300" EventDes="村民在村中意外发了这个道具,如果你可以出个好价格的话，它就是你的了！" />
	<date ID="30020" EventType="3" EventItemID="10020106" EventLv="30" EventPro=".5" EventItemNum="1" CurrencyType="1" CurrencyNum="25200" EventTime="300" EventDes="村民在村中意外发了这个道具,如果你可以出个好价格的话，它就是你的了！" />
	<date ID="30021" EventType="3" EventItemID="10020107" EventLv="32" EventPro=".5" EventItemNum="1" CurrencyType="1" CurrencyNum="37800" EventTime="300" EventDes="村民在村中意外发了这个道具,如果你可以出个好价格的话，它就是你的了！" />
	<date ID="30022" EventType="3" EventItemID="10020110" EventLv="35" EventPro=".5" EventItemNum="1" CurrencyType="1" CurrencyNum="84000" EventTime="300" EventDes="村民在村中意外发了这个道具,如果你可以出个好价格的话，它就是你的了！" />
	<date ID="30023" EventType="3" EventItemID="10010310" EventLv="35" EventPro=".1" EventItemNum="1" CurrencyType="1" CurrencyNum="2325000" EventTime="300" EventDes="村民在村中意外发了这个道具,如果你可以出个好价格的话，它就是你的了！" />
	<date ID="30024" EventType="3" EventItemID="10010311" EventLv="35" EventPro=".1" EventItemNum="1" CurrencyType="1" CurrencyNum="1550000" EventTime="300" EventDes="村民在村中意外发了这个道具,如果你可以出个好价格的话，它就是你的了！" />
	<date ID="30025" EventType="2" EventItemID="10020101" EventLv="30" EventPro="1" EventItemNum="20" CurrencyType="1" CurrencyNum="14600" EventTime="300" EventDes="我现在正在收购这个材料,如果你有的话,我可以高价收购！" />
	<date ID="30026" EventType="2" EventItemID="10020102" EventLv="30" EventPro="1" EventItemNum="20" CurrencyType="1" CurrencyNum="15000" EventTime="300" EventDes="我现在正在收购这个材料,如果你有的话,我可以高价收购！" />
	<date ID="30027" EventType="2" EventItemID="10020103" EventLv="31" EventPro="1" EventItemNum="20" CurrencyType="1" CurrencyNum="15500" EventTime="300" EventDes="我现在正在收购这个材料,如果你有的话,我可以高价收购！" />
	<date ID="30028" EventType="2" EventItemID="10020104" EventLv="32" EventPro="1" EventItemNum="20" CurrencyType="1" CurrencyNum="15900" EventTime="300" EventDes="我现在正在收购这个材料,如果你有的话,我可以高价收购！" />
	<date ID="30029" EventType="2" EventItemID="10020105" EventLv="33" EventPro="1" EventItemNum="20" CurrencyType="1" CurrencyNum="16400" EventTime="300" EventDes="我现在正在收购这个材料,如果你有的话,我可以高价收购！" />
	<date ID="30030" EventType="1" EventItemID="10020101" EventLv="30" EventPro="1" EventItemNum="20" CurrencyType="1" CurrencyNum="7300" EventTime="300" EventDes="村里多了一些材料,就便宜卖给你吧!" />
	<date ID="30031" EventType="1" EventItemID="10020102" EventLv="30" EventPro="1" EventItemNum="20" CurrencyType="1" CurrencyNum="7500" EventTime="300" EventDes="村里多了一些材料,就便宜卖给你吧!" />
	<date ID="30032" EventType="1" EventItemID="10020103" EventLv="31" EventPro="1" EventItemNum="20" CurrencyType="1" CurrencyNum="7750" EventTime="300" EventDes="村里多了一些材料,就便宜卖给你吧!" />
	<date ID="30033" EventType="1" EventItemID="10020104" EventLv="32" EventPro="1" EventItemNum="20" CurrencyType="1" CurrencyNum="7950" EventTime="300" EventDes="村里多了一些材料,就便宜卖给你吧!" />
	<date ID="30034" EventType="1" EventItemID="10020105" EventLv="33" EventPro="1" EventItemNum="20" CurrencyType="1" CurrencyNum="8200" EventTime="300" EventDes="村里多了一些材料,就便宜卖给你吧!" />
	<date ID="40001" EventType="3" EventItemID="10010409" EventLv="40" EventPro=".5" EventItemNum="1" CurrencyType="1" CurrencyNum="90750" EventTime="300" EventDes="村民在村中意外发了这个道具,如果你可以出个好价格的话，它就是你的了！" />
	<date ID="40002" EventType="3" EventItemID="10010410" EventLv="40" EventPro=".5" EventItemNum="1" CurrencyType="1" CurrencyNum="77250" EventTime="300" EventDes="村民在村中意外发了这个道具,如果你可以出个好价格的话，它就是你的了！" />
	<date ID="40003" EventType="3" EventItemID="10010411" EventLv="40" EventPro=".5" EventItemNum="1" CurrencyType="1" CurrencyNum="84000" EventTime="300" EventDes="村民在村中意外发了这个道具,如果你可以出个好价格的话，它就是你的了！" />
	<date ID="40004" EventType="3" EventItemID="10010412" EventLv="45" EventPro=".5" EventItemNum="1" CurrencyType="1" CurrencyNum="90750" EventTime="300" EventDes="村民在村中意外发了这个道具,如果你可以出个好价格的话，它就是你的了！" />
	<date ID="40005" EventType="3" EventItemID="10030501" EventLv="40" EventPro=".5" EventItemNum="1" CurrencyType="1" CurrencyNum="523800" EventTime="300" EventDes="村民在村中意外发了这个道具,如果你可以出个好价格的话，它就是你的了！" />
	<date ID="40006" EventType="3" EventItemID="10030503" EventLv="40" EventPro=".5" EventItemNum="1" CurrencyType="1" CurrencyNum="476400" EventTime="300" EventDes="村民在村中意外发了这个道具,如果你可以出个好价格的话，它就是你的了！" />
	<date ID="40007" EventType="3" EventItemID="10030505" EventLv="40" EventPro=".5" EventItemNum="1" CurrencyType="1" CurrencyNum="381000" EventTime="300" EventDes="村民在村中意外发了这个道具,如果你可以出个好价格的话，它就是你的了！" />
	<date ID="40008" EventType="3" EventItemID="10030507" EventLv="40" EventPro=".5" EventItemNum="1" CurrencyType="1" CurrencyNum="381000" EventTime="300" EventDes="村民在村中意外发了这个道具,如果你可以出个好价格的话，它就是你的了！" />
	<date ID="40009" EventType="3" EventItemID="10030509" EventLv="40" EventPro=".5" EventItemNum="1" CurrencyType="1" CurrencyNum="571800" EventTime="300" EventDes="村民在村中意外发了这个道具,如果你可以出个好价格的话，它就是你的了！" />
	<date ID="40010" EventType="3" EventItemID="10030511" EventLv="40" EventPro=".5" EventItemNum="1" CurrencyType="1" CurrencyNum="619200" EventTime="300" EventDes="村民在村中意外发了这个道具,如果你可以出个好价格的话，它就是你的了！" />
	<date ID="40011" EventType="3" EventItemID="10030513" EventLv="40" EventPro=".5" EventItemNum="1" CurrencyType="1" CurrencyNum="762000" EventTime="300" EventDes="村民在村中意外发了这个道具,如果你可以出个好价格的话，它就是你的了！" />
	<date ID="40012" EventType="3" EventItemID="10030515" EventLv="40" EventPro=".5" EventItemNum="1" CurrencyType="1" CurrencyNum="1810200" EventTime="300" EventDes="村民在村中意外发了这个道具,如果你可以出个好价格的话，它就是你的了！" />
	<date ID="40013" EventType="3" EventItemID="10030516" EventLv="40" EventPro=".5" EventItemNum="1" CurrencyType="1" CurrencyNum="1143600" EventTime="300" EventDes="村民在村中意外发了这个道具,如果你可以出个好价格的话，它就是你的了！" />
	<date ID="40014" EventType="3" EventItemID="10030518" EventLv="40" EventPro=".2" EventItemNum="1" CurrencyType="1" CurrencyNum="2858400" EventTime="300" EventDes="村民在村中意外发了这个道具,如果你可以出个好价格的话，它就是你的了！" />
	<date ID="40015" EventType="3" EventItemID="10030520" EventLv="40" EventPro=".2" EventItemNum="1" CurrencyType="1" CurrencyNum="1429200" EventTime="300" EventDes="村民在村中意外发了这个道具,如果你可以出个好价格的话，它就是你的了！" />
	<date ID="40016" EventType="3" EventItemID="10030519" EventLv="40" EventPro=".5" EventItemNum="1" CurrencyType="1" CurrencyNum="428760" EventTime="300" EventDes="村民在村中意外发了这个道具,如果你可以出个好价格的话，它就是你的了！" />
	<date ID="40017" EventType="3" EventItemID="10010064" EventLv="40" EventPro=".5" EventItemNum="1" CurrencyType="1" CurrencyNum="105480" EventTime="300" EventDes="村民在村中意外发了这个道具,如果你可以出个好价格的话，它就是你的了！" />
	<date ID="40018" EventType="3" EventItemID="10020157" EventLv="40" EventPro=".5" EventItemNum="1" CurrencyType="1" CurrencyNum="47925" EventTime="300" EventDes="村民在村中意外发了这个道具,如果你可以出个好价格的话，它就是你的了！" />
	<date ID="40019" EventType="3" EventItemID="10020161" EventLv="45" EventPro=".5" EventItemNum="1" CurrencyType="1" CurrencyNum="106500" EventTime="300" EventDes="村民在村中意外发了这个道具,如果你可以出个好价格的话，它就是你的了！" />
	<date ID="40020" EventType="3" EventItemID="10010413" EventLv="45" EventPro=".1" EventItemNum="1" CurrencyType="1" CurrencyNum="3487500" EventTime="300" EventDes="村民在村中意外发了这个道具,如果你可以出个好价格的话，它就是你的了！" />
	<date ID="40021" EventType="3" EventItemID="10010414" EventLv="45" EventPro=".1" EventItemNum="1" CurrencyType="1" CurrencyNum="2325000" EventTime="300" EventDes="村民在村中意外发了这个道具,如果你可以出个好价格的话，它就是你的了！" />
	<date ID="40022" EventType="3" EventItemID="10020158" EventLv="40" EventPro=".5" EventItemNum="20" CurrencyType="1" CurrencyNum="6390" EventTime="300" EventDes="村民在村中意外发了这个道具,如果你可以出个好价格的话，它就是你的了！" />
	<date ID="40023" EventType="3" EventItemID="10020159" EventLv="40" EventPro=".5" EventItemNum="20" CurrencyType="1" CurrencyNum="11180" EventTime="300" EventDes="村民在村中意外发了这个道具,如果你可以出个好价格的话，它就是你的了！" />
	<date ID="40024" EventType="2" EventItemID="10020151" EventLv="40" EventPro="1" EventItemNum="20" CurrencyType="1" CurrencyNum="19100" EventTime="300" EventDes="我现在正在收购这个材料,如果你有的话,我可以高价收购！" />
	<date ID="40025" EventType="2" EventItemID="10020152" EventLv="40" EventPro="1" EventItemNum="20" CurrencyType="1" CurrencyNum="19500" EventTime="300" EventDes="我现在正在收购这个材料,如果你有的话,我可以高价收购！" />
	<date ID="40026" EventType="2" EventItemID="10020153" EventLv="42" EventPro="1" EventItemNum="20" CurrencyType="1" CurrencyNum="20400" EventTime="300" EventDes="我现在正在收购这个材料,如果你有的话,我可以高价收购！" />
	<date ID="40027" EventType="2" EventItemID="10020154" EventLv="42" EventPro="1" EventItemNum="20" CurrencyType="1" CurrencyNum="20900" EventTime="300" EventDes="我现在正在收购这个材料,如果你有的话,我可以高价收购！" />
	<date ID="40028" EventType="2" EventItemID="10020155" EventLv="43" EventPro="1" EventItemNum="20" CurrencyType="1" CurrencyNum="21300" EventTime="300" EventDes="我现在正在收购这个材料,如果你有的话,我可以高价收购！" />
	<date ID="40029" EventType="2" EventItemID="10020156" EventLv="41" EventPro="1" EventItemNum="20" CurrencyType="1" CurrencyNum="16000" EventTime="300" EventDes="我现在正在收购这个材料,如果你有的话,我可以高价收购！" />
	<date ID="40030" EventType="2" EventItemID="10020160" EventLv="40" EventPro="1" EventItemNum="20" CurrencyType="1" CurrencyNum="21300" EventTime="300" EventDes="我现在正在收购这个材料,如果你有的话,我可以高价收购！" />
	<date ID="40031" EventType="1" EventItemID="10020151" EventLv="40" EventPro="1" EventItemNum="20" CurrencyType="1" CurrencyNum="9550" EventTime="300" EventDes="村里多了一些材料,就便宜卖给你吧!" />
	<date ID="40032" EventType="1" EventItemID="10020152" EventLv="40" EventPro="1" EventItemNum="20" CurrencyType="1" CurrencyNum="9750" EventTime="300" EventDes="村里多了一些材料,就便宜卖给你吧!" />
	<date ID="40033" EventType="1" EventItemID="10020153" EventLv="42" EventPro="1" EventItemNum="20" CurrencyType="1" CurrencyNum="10200" EventTime="300" EventDes="村里多了一些材料,就便宜卖给你吧!" />
	<date ID="40034" EventType="1" EventItemID="10020154" EventLv="42" EventPro="1" EventItemNum="20" CurrencyType="1" CurrencyNum="10450" EventTime="300" EventDes="村里多了一些材料,就便宜卖给你吧!" />
	<date ID="40035" EventType="1" EventItemID="10020155" EventLv="43" EventPro="1" EventItemNum="20" CurrencyType="1" CurrencyNum="10650" EventTime="300" EventDes="村里多了一些材料,就便宜卖给你吧!" />
	<date ID="40036" EventType="1" EventItemID="10020156" EventLv="41" EventPro="1" EventItemNum="20" CurrencyType="1" CurrencyNum="8000" EventTime="300" EventDes="村里多了一些材料,就便宜卖给你吧!" />
	<date ID="40037" EventType="1" EventItemID="10020160" EventLv="40" EventPro="1" EventItemNum="20" CurrencyType="1" CurrencyNum="10650" EventTime="300" EventDes="村里多了一些材料,就便宜卖给你吧!" />
	<date ID="50001" EventType="3" EventItemID="10030601" EventLv="50" EventPro=".5" EventItemNum="1" CurrencyType="1" CurrencyNum="648000" EventTime="300" EventDes="村民在村中意外发了这个道具,如果你可以出个好价格的话，它就是你的了！" />
	<date ID="50002" EventType="3" EventItemID="10030603" EventLv="50" EventPro=".5" EventItemNum="1" CurrencyType="1" CurrencyNum="589200" EventTime="300" EventDes="村民在村中意外发了这个道具,如果你可以出个好价格的话，它就是你的了！" />
	<date ID="50003" EventType="3" EventItemID="10030605" EventLv="50" EventPro=".5" EventItemNum="1" CurrencyType="1" CurrencyNum="471000" EventTime="300" EventDes="村民在村中意外发了这个道具,如果你可以出个好价格的话，它就是你的了！" />
	<date ID="50004" EventType="3" EventItemID="10030607" EventLv="50" EventPro=".5" EventItemNum="1" CurrencyType="1" CurrencyNum="471000" EventTime="300" EventDes="村民在村中意外发了这个道具,如果你可以出个好价格的话，它就是你的了！" />
	<date ID="50005" EventType="3" EventItemID="10030609" EventLv="50" EventPro=".5" EventItemNum="1" CurrencyType="1" CurrencyNum="706800" EventTime="300" EventDes="村民在村中意外发了这个道具,如果你可以出个好价格的话，它就是你的了！" />
	<date ID="50006" EventType="3" EventItemID="10030611" EventLv="50" EventPro=".5" EventItemNum="1" CurrencyType="1" CurrencyNum="765600" EventTime="300" EventDes="村民在村中意外发了这个道具,如果你可以出个好价格的话，它就是你的了！" />
	<date ID="50007" EventType="3" EventItemID="10030613" EventLv="50" EventPro=".5" EventItemNum="1" CurrencyType="1" CurrencyNum="942000" EventTime="300" EventDes="村民在村中意外发了这个道具,如果你可以出个好价格的话，它就是你的了！" />
	<date ID="50008" EventType="3" EventItemID="10030615" EventLv="50" EventPro=".5" EventItemNum="1" CurrencyType="1" CurrencyNum="2238000" EventTime="300" EventDes="村民在村中意外发了这个道具,如果你可以出个好价格的话，它就是你的了！" />
	<date ID="50009" EventType="3" EventItemID="10030616" EventLv="50" EventPro=".5" EventItemNum="1" CurrencyType="1" CurrencyNum="1413600" EventTime="300" EventDes="村民在村中意外发了这个道具,如果你可以出个好价格的话，它就是你的了！" />
	<date ID="50010" EventType="3" EventItemID="10030618" EventLv="50" EventPro=".2" EventItemNum="1" CurrencyType="1" CurrencyNum="3533400" EventTime="300" EventDes="村民在村中意外发了这个道具,如果你可以出个好价格的话，它就是你的了！" />
	<date ID="50011" EventType="3" EventItemID="10030620" EventLv="50" EventPro=".2" EventItemNum="1" CurrencyType="1" CurrencyNum="1767000" EventTime="300" EventDes="村民在村中意外发了这个道具,如果你可以出个好价格的话，它就是你的了！" />
	<date ID="50012" EventType="3" EventItemID="10010065" EventLv="50" EventPro=".5" EventItemNum="1" CurrencyType="1" CurrencyNum="185640" EventTime="300" EventDes="村民在村中意外发了这个道具,如果你可以出个好价格的话，它就是你的了！" />
	<date ID="50013" EventType="3" EventItemID="10020213" EventLv="50" EventPro=".5" EventItemNum="20" CurrencyType="1" CurrencyNum="7740" EventTime="300" EventDes="村民在村中意外发了这个道具,如果你可以出个好价格的话，它就是你的了！" />
	<date ID="50014" EventType="3" EventItemID="10020214" EventLv="50" EventPro=".5" EventItemNum="20" CurrencyType="1" CurrencyNum="13550" EventTime="300" EventDes="村民在村中意外发了这个道具,如果你可以出个好价格的话，它就是你的了！" />
	<date ID="50015" EventType="3" EventItemID="10020208" EventLv="52" EventPro=".5" EventItemNum="1" CurrencyType="1" CurrencyNum="58050" EventTime="300" EventDes="村民在村中意外发了这个道具,如果你可以出个好价格的话，它就是你的了！" />
	<date ID="50016" EventType="3" EventItemID="10020215" EventLv="55" EventPro=".5" EventItemNum="1" CurrencyType="1" CurrencyNum="226140" EventTime="300" EventDes="村民在村中意外发了这个道具,如果你可以出个好价格的话，它就是你的了！" />
	<date ID="50017" EventType="3" EventItemID="10020216" EventLv="55" EventPro=".5" EventItemNum="1" CurrencyType="1" CurrencyNum="407940" EventTime="300" EventDes="村民在村中意外发了这个道具,如果你可以出个好价格的话，它就是你的了！" />
	<date ID="50018" EventType="2" EventItemID="10020201" EventLv="50" EventPro="1" EventItemNum="20" CurrencyType="1" CurrencyNum="23600" EventTime="300" EventDes="我现在正在收购这个材料,如果你有的话,我可以高价收购！" />
	<date ID="50019" EventType="2" EventItemID="10020202" EventLv="50" EventPro="1" EventItemNum="20" CurrencyType="1" CurrencyNum="24000" EventTime="300" EventDes="我现在正在收购这个材料,如果你有的话,我可以高价收购！" />
	<date ID="50020" EventType="2" EventItemID="10020203" EventLv="52" EventPro="1" EventItemNum="20" CurrencyType="1" CurrencyNum="24500" EventTime="300" EventDes="我现在正在收购这个材料,如果你有的话,我可以高价收购！" />
	<date ID="50021" EventType="2" EventItemID="10020204" EventLv="52" EventPro="1" EventItemNum="20" CurrencyType="1" CurrencyNum="24900" EventTime="300" EventDes="我现在正在收购这个材料,如果你有的话,我可以高价收购！" />
	<date ID="50022" EventType="2" EventItemID="10020205" EventLv="52" EventPro="1" EventItemNum="20" CurrencyType="1" CurrencyNum="18700" EventTime="300" EventDes="我现在正在收购这个材料,如果你有的话,我可以高价收购！" />
	<date ID="50023" EventType="2" EventItemID="10020206" EventLv="52" EventPro="1" EventItemNum="20" CurrencyType="1" CurrencyNum="25800" EventTime="300" EventDes="我现在正在收购这个材料,如果你有的话,我可以高价收购！" />
	<date ID="50024" EventType="2" EventItemID="10020207" EventLv="50" EventPro="1" EventItemNum="20" CurrencyType="1" CurrencyNum="77400" EventTime="300" EventDes="我现在正在收购这个材料,如果你有的话,我可以高价收购！" />
	<date ID="50025" EventType="1" EventItemID="10020201" EventLv="50" EventPro="1" EventItemNum="20" CurrencyType="1" CurrencyNum="11800" EventTime="300" EventDes="村里多了一些材料,就便宜卖给你吧!" />
	<date ID="50026" EventType="1" EventItemID="10020202" EventLv="50" EventPro="1" EventItemNum="20" CurrencyType="1" CurrencyNum="12000" EventTime="300" EventDes="村里多了一些材料,就便宜卖给你吧!" />
	<date ID="50027" EventType="1" EventItemID="10020203" EventLv="52" EventPro="1" EventItemNum="20" CurrencyType="1" CurrencyNum="12250" EventTime="300" EventDes="村里多了一些材料,就便宜卖给你吧!" />
	<date ID="50028" EventType="1" EventItemID="10020204" EventLv="52" EventPro="1" EventItemNum="20" CurrencyType="1" CurrencyNum="12450" EventTime="300" EventDes="村里多了一些材料,就便宜卖给你吧!" />
	<date ID="50029" EventType="1" EventItemID="10020205" EventLv="52" EventPro="1" EventItemNum="20" CurrencyType="1" CurrencyNum="9350" EventTime="300" EventDes="村里多了一些材料,就便宜卖给你吧!" />
	<date ID="50030" EventType="1" EventItemID="10020206" EventLv="52" EventPro="1" EventItemNum="20" CurrencyType="1" CurrencyNum="12900" EventTime="300" EventDes="村里多了一些材料,就便宜卖给你吧!" />
	<date ID="50031" EventType="1" EventItemID="10020207" EventLv="50" EventPro="1" EventItemNum="20" CurrencyType="1" CurrencyNum="38700" EventTime="300" EventDes="村里多了一些材料,就便宜卖给你吧!" />
</DateArea>